AMCowmvg/__init__.py
AMCowmvg/antimonyTools.py
AMCowmvg/forms.py
AMCowmvg/routes.py
AMCowmvg/testing.py
AMCowmvg/static/antimony1.txt
AMCowmvg/static/antimony2.txt
AMCowmvg/static/output.jpg
AMCowmvg/static/test.txt
AMCowmvg/templates/buildSystem.html
AMCowmvg/templates/home.html
AMCowmvg/templates/results.html
AMCowmvg/templates/testing.html
AMCowmvg-1.1.0.dist-info/LICENSE
AMCowmvg-1.1.0.dist-info/METADATA
AMCowmvg-1.1.0.dist-info/WHEEL
AMCowmvg-1.1.0.dist-info/top_level.txt
AMCowmvg-1.1.0.dist-info/RECORD
