Metadata-Version: 2.1
Name: AMCowmvg
Version: 1.1.0
Summary: Produce Antimony Files and Graphs using a browser GUI
Author-email: Olivia Walsh <owalsh@uw.edu>, Matthew Van Ginneken <mattcvang@gmail.com>
License: MIT License
Project-URL: Homepage, https://github.com/MatthewVanG/AMC-OWMVG
Requires-Python: >=3.6
License-File: LICENSE
Requires-Dist: tellurium
Requires-Dist: flask
Requires-Dist: wtforms
Requires-Dist: flask-wtf
Requires-Dist: matplotlib
